[{"name":"CoinTab Web","address":"https://cointab.winter100.com/","logo":"cointab.png?t=1","description":{"en_US":"A personalized new tab page for cryptocurrency enthusiasts, free to add markets, websites, HD wallpapers, provide profit analysis and early warnings, and help you keep abreast of market changes","zh_Hans_CN":"加密资产爱好者的个性新标签页，自由添加市场，网站，高清壁纸，提供盈亏分析和预警，随时了解市场变化","zh_Hant_HK":"加密資產愛好者的個性新標簽頁，自由添加市場，網站，高清壁紙，提供盈虧分析和預警，隨時了解市場變化"},"tags":["popular"]},{"name":"Binance","address":"https://www.binance.com?ref=28672219","logo":"binance.svg","description":"Buy, trade, and hold 350+ cryptocurrencies on Binance","tags":["exchange","popular"]},{"name":"CoinEx","address":"https://www.coinex.com?refer_code=p9uec","logo":"coinex.svg","description":{"en_US":"The Global Cryptocurrency Exchange","zh_Hans_CN":"全球数字资产交易平台，让加密资产交易更简单","zh_Hant_HK":"全球數字資產交易平台，讓加密資產交易更簡單"},"tags":["popular","exchange"]},{ "name":"NEXO", "address":"https://nexo.com/ref/4owrbxa0fz?src=web-link", "logo":"https://cointab.winter100.com/assets/app/logo/nexo.svg","tags":["popular","exchange"] },{"name":"OKX","address":"https://www.okx.com","logo":"okx.svg","description":"","tags":["exchange","popular"]},{"name":"Coinbase","address":"https://pro.coinbase.com","logo":"https://s2.coinmarketcap.com/static/img/exchanges/64x64/89.png","description":"","tags":["exchange"]},{"name":"Gate.io","address":"https://gate.io/","logo":"https://s2.coinmarketcap.com/static/img/exchanges/64x64/302.png","description":"","tags":["exchange"]},{"name":"Kraken","address":"https://www.kraken.com","logo":"https://s2.coinmarketcap.com/static/img/exchanges/64x64/24.png","description":"","tags":["exchange"]},{"name":"Huobi Global","address":"https://www.huobi.com/","logo":"https://s2.coinmarketcap.com/static/img/exchanges/64x64/102.png","description":"","tags":["exchange"]},{"name":"Uniswap","address":"https://app.uniswap.org/#/swap","logo":"uni.png","description":"","tags":["dex","popular"]},{"name":"dYdX","address":"https://dydx.exchange/r/EOWRNLEF","logo":"dydx.png","description":"","tags":["dex"]},{"name":"PancakeSwap (V2)","address":"https://pancakeswap.finance/","logo":"cake.png","description":"","tags":["dex","nft"]},{"name":"OneSwap","address":"https://www.oneswap.net/cet?r=10002651","logo":"ones.png","description":"","tags":["dex","nft","popular"]},{"name":"SushiSwap","address":"https://app.sushi.com/swap","logo":"sushi.png","description":"","tags":["dex"]},{"name":"Sun.io","address":"https://s2.coinmarketcap.com/static/img/exchanges/64x64/1116.png","logo":"https://s2.coinmarketcap.com/static/img/exchanges/64x64/1116.png","description":"","tags":["dex"]},{"name":"GitHub","address":"https://github.com/","logo":"other/GitHub.svg","description":"","tags":["social","popular"]},{"name":"YouTuBe","address":"https://www.youtube.com/","logo":"https://www.youtube.com/s/desktop/79928844/img/favicon_144x144.png","description":"","tags":["social","popular"]},{"name":"Twitter","address":"https://twitter.com/","logo":"other/twitter.png","description":"","tags":["social","popular"]},{"name":"Facebook","address":"https://www.facebook.com/","logo":"other/Facebook.svg","description":"","tags":["social","popular"]},{"name":"Medium","address":"https://medium.com/","logo":"other/medium.png","description":"","tags":["social"]},{"name":"V2EX","address":"https://www.v2ex.com/","logo":"https://www.v2ex.com/static/icon-192.png","description":"","tags":["social"]},{"name":"Instagram","address":"https://www.instagram.com/","logo":"other/Instagram.png","description":"","tags":["social"]},{"name":"reddit","address":"https://www.reddit.com/","logo":"https://www.redditstatic.com/desktop2x/img/favicon/apple-icon-152x152.png","description":"","tags":["social"]},{"name":"微博","address":"https://weibo.com/","logo":"other/weibo.svg","description":"","tags":["social"]},{"name":"知乎","address":"https://www.zhihu.com/","logo":"other/zhihu.svg","description":"","tags":["social"]},{"name":"Etherscan","address":"https://etherscan.io/","logo":"https://etherscan.io/images/brandassets/etherscan-logo-circle.jpg","description":" Ethereum (ETH) Blockchain Explorer","tags":["explorer","popular"]},{"name":"ViaWallet Explorer","address":"https://explorer.viawallet.com/","logo":"https://bridge.coinex.net/images/header/viawallet-logo.svg","description":"ViaWallet Blockchain Explorer","tags":["explorer","popular"]},{"name":"TRONSCAN","address":"https://tronscan.org/","logo":"https://tronscan.org/favicon.png?v=2","description":"TRON BlockChain Explorer","tags":["explorer","popular"]},{"name":"BscScan","address":"https://bscscan.com/","logo":"https://BscScan.com/images/brandassets/BscScan-logo-circle.jpg","description":"Binance (BNB) Blockchain Explorer","tags":["explorer","popular"]},{"name":"Btc.com","address":"https://explorer.btc.com/","logo":"https://explorer.btc.com/favicon.ico","description":"","tags":["explorer"]},{"name":"CMC Explorer","address":"https://blockchain.coinmarketcap.com/","logo":"https://blockchain.coinmarketcap.com/static/favicon.ico","description":"CoinMarketCap BlockChain Explorer","tags":["explorer"]},{"name":"CoinMarketCap","address":"https://coinmarketcap.com/","logo":"https://coinmarketcap.com/apple-touch-icon.png","description":"Top cryptocurrency prices and charts, listed by market capitalization.","tags":["news","popular"]},{"name":"crypto.news","address":"https://crypto.news/","logo":"https://crypto.news/app/uploads/2022/01/cropped-cryptonews-icon-180x180.png","description":"Get latest & hot crypto news","tags":["news"]},{"name":"CoinGape","address":"https://coingape.com/","logo":"https://cdn.coingape.com/wp-content/uploads/2017/09/14183030/cropped-CoinGape_logo-192x192.png","description":"Bitcoin, Ethereum, Crypto News and Price Analysis","tags":["news"]},{"name":"非小号","address":"https://www.feixiaohaozh.info/","logo":"https://www.feixiaohaozh.info/favicon.svg","description":"","tags":["news"]},{"name":"Crypto Daily™","address":"https://cryptodaily.co.uk/","logo":"https://cryptodaily.co.uk/assets/cryptodaily/img/cryptodaily-favicon-32x32.jpg","description":"Top Crypto and Blockchain News","tags":["news"]},{"name":"DappRadar","address":"https://dappradar.com/","logo":"https://dappradar.com/public-assets/apple-touch-icon.png","description":"The World’s Dapp Store & Blockchain Dapps Ranked","tags":["news"]},{"name":"CryptoRank","address":"https://cryptorank.io/","logo":"https://cryptorank.io/static/logo.png","description":"Cryptocurrency Market Capitalization ✔ Coin ratings","tags":["news"]},{"name":"PolygonScan","address":"https://polygonscan.com/","logo":"https://polygonscan.com/images/svg/brands/polygon.svg","description":"Polygon (MATIC) Blockchain Explorer","tags":["explorer"]},{"name":"SnowTrace","address":"https://snowtrace.io/","logo":"https://snowtrace.io/images/favicon.ico?v=22.11.2.0","description":"Avalanche (AVAX) C-Chain Blockchain Explorer","tags":["explorer"]},{"name":"Solana Explorer","address":"https://explorer.solana.com/","logo":"https://explorer.solana.com/favicon.ico","description":"Solana (SOL) Blockchain Explorer","tags":["explorer"]},{"name":"ViaBTC","address":"https://www.viabtc.com/","logo":"https://www.viabtc.com/images/brand/png/c.png","description":{"en_US":"Bitcoin, Litecoin, Comprehensive Global Cryptocurrency Mining Pool","zh_Hans_CN":"比特币、莱特币、服务全球的综合性数字货币矿池","zh_Hant_HK":"比特幣、萊特幣、服務全球的綜合性數字貨幣礦池"},"tags":["pool","popular"]},{"name":"AntPool","address":"https://www.antpool.com/","logo":"https://www.antpool.com/logo-120.png","description":"World Leading BTC Mining Pool","tags":["pool","popular"]},{"name":"foundry","address":"https://foundrydigital.com/","logo":"https://foundrydigital.com/icons/icon-96x96.png?v=1ef1b1af0aa84f190652a82af20f332a","description":"Empowering a decentralized infrastructure","tags":["pool"]},{"name":"F2Pool","address":"https://www.f2pool.com/","logo":"https://static.f2pool.com/static/images/apple-icon-114.png?v=5b18823b70e70c2063ac8381c5164776","description":"A geographically distributed mining pool","tags":["pool"]},{"name":"BRAIINS POOL","address":"https://braiins.com/","logo":"https://assets.website-files.com/5e5ee6f9b325a6509259421f/5f8438e2c6be0ee267da273e_II%20logo%402x.png","description":"Bitcoin mining company","tags":["pool"]},{"name":"opensea","address":"https://opensea.io/","logo":"https://opensea.io/static/images/favicon/180x180.png","description":"The largest NFT marketplace","tags":["nft"]},{"name":"CSC Explorer","address":"https://www.coinex.net/","logo":"https://www.coinex.net/favicon.ico","description":"CoinEx Smart Chain（CSC）Explorer","tags":["explorer","popular"]},{"name":"MetaMask","address":"https://metamask.io/","logo":"https://metamask.io/icons/icon-144x144.png?v=48400a28770e10dd52a8c0e539aeb282","description":"The crypto wallet for Defi, Web3 Dapps and NFTs","tags":["wallet","popular"]},{"name":"ViaWallet","address":"https://viawallet.com/","logo":"https://bridge.coinex.net/images/header/viawallet-logo.svg","description":{"en_US":"Secure Multi-chain & Multi-cryptocurrency Wallet","zh_Hans_CN":"专业安全的多链多币种加密货币钱包","zh_Hant_HK":"專業安全的多鏈多幣種加密貨幣錢包"},"tags":["wallet","popular"]},{"name":"Trust","address":"https://trustwallet.com/","logo":"https://trustwallet.com/assets/images/favicon.png","description":"Cryptocurrency Wallet, Ethereum Wallet, ERC20 Wallet","tags":["wallet","popular"]},{"name":"Coinbase","address":"https://www.coinbase.com/wallet","logo":"https://assets.coinbase.com/assets/favicon-128.96b5e5938ce0457adc15f5911a384f49.png","description":"A secure online platform for buying, selling, transferring, and storing cryptocurrency","tags":["wallet","popular"]}]
